README.md
setup.py
genie_aladdin/__init__.py
genie_aladdin/api.py
genie_aladdin.egg-info/PKG-INFO
genie_aladdin.egg-info/SOURCES.txt
genie_aladdin.egg-info/dependency_links.txt
genie_aladdin.egg-info/top_level.txt