Metadata-Version: 2.1
Name: genie-aladdin
Version: 2020.5.1
Summary: Client for connecting to the Genie Aladdin connected garage door opener
Home-page: https://github.com/pypa/genie_aladdin
Author: Aijay Adams
Author-email: aijay.adams@gmail.com
License: UNKNOWN
Platform: UNKNOWN
Classifier: Programming Language :: Python :: 3
Classifier: License :: OSI Approved :: MIT License
Classifier: Operating System :: OS Independent
Requires-Python: >=3.7
